<?xml version="1.0" encoding="UTF-8" standalone="yes" ?>
<!DOCTYPE boost_serialization>
<boost_serialization signature="serialization::archive" version="9">
<tracklets class_id="0" tracking_level="0" version="0">
	<count>1</count>
	<item_version>1</item_version> 
	<item class_id="1" tracking_level="0" version="1">
		<objectType>Car</objectType>
		<h>1.397000</h>
		<w>1.701800</w>
		<l>4.521200</l>
		<first_frame>0</first_frame>
		<poses class_id="2" tracking_level="0" version="0">
			<count>77</count>
			<item_version>2</item_version>
			<item class_id="3" tracking_level="0" version="2">
				<tx>21.312886</tx>
				<ty>3.732551</ty>
				<tz>-0.439862</tz>
				<rx>0.000000</rx>
				<ry>-0.000000</ry>
				<rz>3.106017</rz>
				<state>1</state>
				<occlusion>-1</occlusion>
				<occlusion_kf>-1</occlusion_kf>
				<truncation>-1</truncation>
				<amt_occlusion>0.0</amt_occlusion>
				<amt_occlusion_kf>-1</amt_occlusion_kf>
				<amt_border_l>0.0</amt_border_l>
				<amt_border_r>0.0</amt_border_r>
				<amt_border_kf>-1</amt_border_kf>
			</item>
			<item>
				<tx>19.861222</tx>
				<ty>3.660672</ty>
				<tz>-0.458369</tz>
				<rx>0.000000</rx>
				<ry>-0.000000</ry>
				<rz>3.102341</rz>
				<state>1</state>
				<occlusion>-1</occlusion>
				<occlusion_kf>-1</occlusion_kf>
				<truncation>-1</truncation>
				<amt_occlusion>0.0</amt_occlusion>
				<amt_occlusion_kf>-1</amt_occlusion_kf>
				<amt_border_l>0.0</amt_border_l>
				<amt_border_r>0.0</amt_border_r>
				<amt_border_kf>-1</amt_border_kf>
			</item>
			<item>
				<tx>18.501385</tx>
				<ty>3.649280</ty>
				<tz>-0.471018</tz>
				<rx>0.000000</rx>
				<ry>-0.000000</ry>
				<rz>3.100275</rz>
				<state>1</state>
				<occlusion>-1</occlusion>
				<occlusion_kf>-1</occlusion_kf>
				<truncation>-1</truncation>
				<amt_occlusion>0.0</amt_occlusion>
				<amt_occlusion_kf>-1</amt_occlusion_kf>
				<amt_border_l>0.0</amt_border_l>
				<amt_border_r>0.0</amt_border_r>
				<amt_border_kf>-1</amt_border_kf>
			</item>
			<item>
				<tx>17.276135</tx>
				<ty>3.661602</ty>
				<tz>-0.485569</tz>
				<rx>0.000000</rx>
				<ry>-0.000000</ry>
				<rz>3.094701</rz>
				<state>1</state>
				<occlusion>-1</occlusion>
				<occlusion_kf>-1</occlusion_kf>
				<truncation>-1</truncation>
				<amt_occlusion>0.0</amt_occlusion>
				<amt_occlusion_kf>-1</amt_occlusion_kf>
				<amt_border_l>0.0</amt_border_l>
				<amt_border_r>0.0</amt_border_r>
				<amt_border_kf>-1</amt_border_kf>
			</item>
			<item>
				<tx>15.985375</tx>
				<ty>3.668944</ty>
				<tz>-0.507705</tz>
				<rx>0.000000</rx>
				<ry>-0.000000</ry>
				<rz>3.093192</rz>
				<state>1</state>
				<occlusion>-1</occlusion>
				<occlusion_kf>-1</occlusion_kf>
				<truncation>-1</truncation>
				<amt_occlusion>0.0</amt_occlusion>
				<amt_occlusion_kf>-1</amt_occlusion_kf>
				<amt_border_l>0.0</amt_border_l>
				<amt_border_r>0.0</amt_border_r>
				<amt_border_kf>-1</amt_border_kf>
			</item>
			<item>
				<tx>14.364766</tx>
				<ty>3.664977</ty>
				<tz>-0.540081</tz>
				<rx>0.000000</rx>
				<ry>-0.000000</ry>
				<rz>3.088655</rz>
				<state>1</state>
				<occlusion>-1</occlusion>
				<occlusion_kf>-1</occlusion_kf>
				<truncation>-1</truncation>
				<amt_occlusion>0.0</amt_occlusion>
				<amt_occlusion_kf>-1</amt_occlusion_kf>
				<amt_border_l>0.0</amt_border_l>
				<amt_border_r>0.0</amt_border_r>
				<amt_border_kf>-1</amt_border_kf>
			</item>
			<item>
				<tx>12.933439</tx>
				<ty>3.690479</ty>
				<tz>-0.559820</tz>
				<rx>0.000000</rx>
				<ry>-0.000000</ry>
				<rz>3.088031</rz>
				<state>1</state>
				<occlusion>-1</occlusion>
				<occlusion_kf>-1</occlusion_kf>
				<truncation>-1</truncation>
				<amt_occlusion>0.0</amt_occlusion>
				<amt_occlusion_kf>-1</amt_occlusion_kf>
				<amt_border_l>0.0</amt_border_l>
				<amt_border_r>0.0</amt_border_r>
				<amt_border_kf>-1</amt_border_kf>
			</item>
			<item>
				<tx>11.489599</tx>
				<ty>3.729969</ty>
				<tz>-0.583166</tz>
				<rx>0.000000</rx>
				<ry>-0.000000</ry>
				<rz>3.093924</rz>
				<state>1</state>
				<occlusion>-1</occlusion>
				<occlusion_kf>-1</occlusion_kf>
				<truncation>-1</truncation>
				<amt_occlusion>0.0</amt_occlusion>
				<amt_occlusion_kf>-1</amt_occlusion_kf>
				<amt_border_l>0.0</amt_border_l>
				<amt_border_r>0.0</amt_border_r>
				<amt_border_kf>-1</amt_border_kf>
			</item>
			<item>
				<tx>10.049808</tx>
				<ty>3.780094</ty>
				<tz>-0.609022</tz>
				<rx>0.000000</rx>
				<ry>-0.000000</ry>
				<rz>3.097371</rz>
				<state>1</state>
				<occlusion>-1</occlusion>
				<occlusion_kf>-1</occlusion_kf>
				<truncation>-1</truncation>
				<amt_occlusion>0.0</amt_occlusion>
				<amt_occlusion_kf>-1</amt_occlusion_kf>
				<amt_border_l>0.0</amt_border_l>
				<amt_border_r>0.0</amt_border_r>
				<amt_border_kf>-1</amt_border_kf>
			</item>
			<item>
				<tx>8.607066</tx>
				<ty>3.816591</ty>
				<tz>-0.636521</tz>
				<rx>0.000000</rx>
				<ry>-0.000000</ry>
				<rz>3.090734</rz>
				<state>1</state>
				<occlusion>-1</occlusion>
				<occlusion_kf>-1</occlusion_kf>
				<truncation>-1</truncation>
				<amt_occlusion>0.0</amt_occlusion>
				<amt_occlusion_kf>-1</amt_occlusion_kf>
				<amt_border_l>0.0</amt_border_l>
				<amt_border_r>0.0</amt_border_r>
				<amt_border_kf>-1</amt_border_kf>
			</item>
			<item>
				<tx>7.158304</tx>
				<ty>3.871229</ty>
				<tz>-0.661712</tz>
				<rx>0.000000</rx>
				<ry>-0.000000</ry>
				<rz>3.085410</rz>
				<state>1</state>
				<occlusion>-1</occlusion>
				<occlusion_kf>-1</occlusion_kf>
				<truncation>-1</truncation>
				<amt_occlusion>0.0</amt_occlusion>
				<amt_occlusion_kf>-1</amt_occlusion_kf>
				<amt_border_l>0.0</amt_border_l>
				<amt_border_r>0.0</amt_border_r>
				<amt_border_kf>-1</amt_border_kf>
			</item>
			<item>
				<tx>5.681152</tx>
				<ty>3.920818</ty>
				<tz>-0.690474</tz>
				<rx>0.000000</rx>
				<ry>-0.000000</ry>
				<rz>3.090638</rz>
				<state>1</state>
				<occlusion>-1</occlusion>
				<occlusion_kf>-1</occlusion_kf>
				<truncation>-1</truncation>
				<amt_occlusion>0.0</amt_occlusion>
				<amt_occlusion_kf>-1</amt_occlusion_kf>
				<amt_border_l>0.0</amt_border_l>
				<amt_border_r>0.0</amt_border_r>
				<amt_border_kf>-1</amt_border_kf>
			</item>
			<item>
				<tx>4.202917</tx>
				<ty>3.935248</ty>
				<tz>-0.730961</tz>
				<rx>0.000000</rx>
				<ry>-0.000000</ry>
				<rz>3.097531</rz>
				<state>1</state>
				<occlusion>-1</occlusion>
				<occlusion_kf>-1</occlusion_kf>
				<truncation>-1</truncation>
				<amt_occlusion>0.0</amt_occlusion>
				<amt_occlusion_kf>-1</amt_occlusion_kf>
				<amt_border_l>0.0</amt_border_l>
				<amt_border_r>0.0</amt_border_r>
				<amt_border_kf>-1</amt_border_kf>
			</item>
			<item>
				<tx>2.893110</tx>
				<ty>3.948652</ty>
				<tz>-0.766451</tz>
				<rx>0.000000</rx>
				<ry>-0.000000</ry>
				<rz>3.093853</rz>
				<state>1</state>
				<occlusion>-1</occlusion>
				<occlusion_kf>-1</occlusion_kf>
				<truncation>-1</truncation>
				<amt_occlusion>0.0</amt_occlusion>
				<amt_occlusion_kf>-1</amt_occlusion_kf>
				<amt_border_l>0.0</amt_border_l>
				<amt_border_r>0.0</amt_border_r>
				<amt_border_kf>-1</amt_border_kf>
			</item>
			<item>
				<tx>1.494295</tx>
				<ty>3.971242</ty>
				<tz>-0.783075</tz>
				<rx>0.000000</rx>
				<ry>-0.000000</ry>
				<rz>3.084469</rz>
				<state>1</state>
				<occlusion>-1</occlusion>
				<occlusion_kf>-1</occlusion_kf>
				<truncation>-1</truncation>
				<amt_occlusion>0.0</amt_occlusion>
				<amt_occlusion_kf>-1</amt_occlusion_kf>
				<amt_border_l>0.0</amt_border_l>
				<amt_border_r>0.0</amt_border_r>
				<amt_border_kf>-1</amt_border_kf>
			</item>
			<item>
				<tx>-0.260539</tx>
				<ty>4.011142</ty>
				<tz>-0.796739</tz>
				<rx>0.000000</rx>
				<ry>-0.000000</ry>
				<rz>3.082592</rz>
				<state>1</state>
				<occlusion>-1</occlusion>
				<occlusion_kf>-1</occlusion_kf>
				<truncation>-1</truncation>
				<amt_occlusion>0.0</amt_occlusion>
				<amt_occlusion_kf>-1</amt_occlusion_kf>
				<amt_border_l>0.0</amt_border_l>
				<amt_border_r>0.0</amt_border_r>
				<amt_border_kf>-1</amt_border_kf>
			</item>
			<item>
				<tx>-1.745540</tx>
				<ty>4.045555</ty>
				<tz>-0.831771</tz>
				<rx>0.000000</rx>
				<ry>-0.000000</ry>
				<rz>3.087206</rz>
				<state>1</state>
				<occlusion>-1</occlusion>
				<occlusion_kf>-1</occlusion_kf>
				<truncation>-1</truncation>
				<amt_occlusion>0.0</amt_occlusion>
				<amt_occlusion_kf>-1</amt_occlusion_kf>
				<amt_border_l>0.0</amt_border_l>
				<amt_border_r>0.0</amt_border_r>
				<amt_border_kf>-1</amt_border_kf>
			</item>
			<item>
				<tx>-3.243850</tx>
				<ty>4.075819</ty>
				<tz>-0.862056</tz>
				<rx>0.000000</rx>
				<ry>-0.000000</ry>
				<rz>3.087758</rz>
				<state>1</state>
				<occlusion>-1</occlusion>
				<occlusion_kf>-1</occlusion_kf>
				<truncation>-1</truncation>
				<amt_occlusion>0.0</amt_occlusion>
				<amt_occlusion_kf>-1</amt_occlusion_kf>
				<amt_border_l>0.0</amt_border_l>
				<amt_border_r>0.0</amt_border_r>
				<amt_border_kf>-1</amt_border_kf>
			</item>
			<item>
				<tx>-4.748417</tx>
				<ty>4.106391</ty>
				<tz>-0.891630</tz>
				<rx>0.000000</rx>
				<ry>-0.000000</ry>
				<rz>3.086730</rz>
				<state>1</state>
				<occlusion>-1</occlusion>
				<occlusion_kf>-1</occlusion_kf>
				<truncation>-1</truncation>
				<amt_occlusion>0.0</amt_occlusion>
				<amt_occlusion_kf>-1</amt_occlusion_kf>
				<amt_border_l>0.0</amt_border_l>
				<amt_border_r>0.0</amt_border_r>
				<amt_border_kf>-1</amt_border_kf>
			</item>
			<item>
				<tx>-6.176634</tx>
				<ty>4.141212</ty>
				<tz>-0.922704</tz>
				<rx>0.000000</rx>
				<ry>-0.000000</ry>
				<rz>3.088218</rz>
				<state>1</state>
				<occlusion>-1</occlusion>
				<occlusion_kf>-1</occlusion_kf>
				<truncation>-1</truncation>
				<amt_occlusion>0.0</amt_occlusion>
				<amt_occlusion_kf>-1</amt_occlusion_kf>
				<amt_border_l>0.0</amt_border_l>
				<amt_border_r>0.0</amt_border_r>
				<amt_border_kf>-1</amt_border_kf>
			</item>
			<item>
				<tx>-7.660868</tx>
				<ty>4.180170</ty>
				<tz>-0.950601</tz>
				<rx>0.000000</rx>
				<ry>-0.000000</ry>
				<rz>3.086171</rz>
				<state>1</state>
				<occlusion>-1</occlusion>
				<occlusion_kf>-1</occlusion_kf>
				<truncation>-1</truncation>
				<amt_occlusion>0.0</amt_occlusion>
				<amt_occlusion_kf>-1</amt_occlusion_kf>
				<amt_border_l>0.0</amt_border_l>
				<amt_border_r>0.0</amt_border_r>
				<amt_border_kf>-1</amt_border_kf>
			</item>
			<item>
				<tx>-9.262781</tx>
				<ty>4.212936</ty>
				<tz>-0.970045</tz>
				<rx>0.000000</rx>
				<ry>-0.000000</ry>
				<rz>3.081021</rz>
				<state>1</state>
				<occlusion>-1</occlusion>
				<occlusion_kf>-1</occlusion_kf>
				<truncation>-1</truncation>
				<amt_occlusion>0.0</amt_occlusion>
				<amt_occlusion_kf>-1</amt_occlusion_kf>
				<amt_border_l>0.0</amt_border_l>
				<amt_border_r>0.0</amt_border_r>
				<amt_border_kf>-1</amt_border_kf>
			</item>
			<item>
				<tx>-10.777365</tx>
				<ty>4.252708</ty>
				<tz>-0.995042</tz>
				<rx>0.000000</rx>
				<ry>-0.000000</ry>
				<rz>3.078932</rz>
				<state>1</state>
				<occlusion>-1</occlusion>
				<occlusion_kf>-1</occlusion_kf>
				<truncation>-1</truncation>
				<amt_occlusion>0.0</amt_occlusion>
				<amt_occlusion_kf>-1</amt_occlusion_kf>
				<amt_border_l>0.0</amt_border_l>
				<amt_border_r>0.0</amt_border_r>
				<amt_border_kf>-1</amt_border_kf>
			</item>
			<item>
				<tx>-12.101093</tx>
				<ty>4.296165</ty>
				<tz>-1.023182</tz>
				<rx>0.000000</rx>
				<ry>-0.000000</ry>
				<rz>3.078427</rz>
				<state>1</state>
				<occlusion>-1</occlusion>
				<occlusion_kf>-1</occlusion_kf>
				<truncation>-1</truncation>
				<amt_occlusion>0.0</amt_occlusion>
				<amt_occlusion_kf>-1</amt_occlusion_kf>
				<amt_border_l>0.0</amt_border_l>
				<amt_border_r>0.0</amt_border_r>
				<amt_border_kf>-1</amt_border_kf>
			</item>
			<item>
				<tx>-13.498083</tx>
				<ty>4.345956</ty>
				<tz>-1.066006</tz>
				<rx>0.000000</rx>
				<ry>-0.000000</ry>
				<rz>3.076225</rz>
				<state>1</state>
				<occlusion>-1</occlusion>
				<occlusion_kf>-1</occlusion_kf>
				<truncation>-1</truncation>
				<amt_occlusion>0.0</amt_occlusion>
				<amt_occlusion_kf>-1</amt_occlusion_kf>
				<amt_border_l>0.0</amt_border_l>
				<amt_border_r>0.0</amt_border_r>
				<amt_border_kf>-1</amt_border_kf>
			</item>
			<item>
				<tx>-15.267937</tx>
				<ty>4.385601</ty>
				<tz>-1.134117</tz>
				<rx>0.000000</rx>
				<ry>-0.000000</ry>
				<rz>3.077745</rz>
				<state>1</state>
				<occlusion>-1</occlusion>
				<occlusion_kf>-1</occlusion_kf>
				<truncation>-1</truncation>
				<amt_occlusion>0.0</amt_occlusion>
				<amt_occlusion_kf>-1</amt_occlusion_kf>
				<amt_border_l>0.0</amt_border_l>
				<amt_border_r>0.0</amt_border_r>
				<amt_border_kf>-1</amt_border_kf>
			</item>
			<item>
				<tx>-16.756667</tx>
				<ty>4.420209</ty>
				<tz>-1.178873</tz>
				<rx>0.000000</rx>
				<ry>-0.000000</ry>
				<rz>3.078968</rz>
				<state>1</state>
				<occlusion>-1</occlusion>
				<occlusion_kf>-1</occlusion_kf>
				<truncation>-1</truncation>
				<amt_occlusion>0.0</amt_occlusion>
				<amt_occlusion_kf>-1</amt_occlusion_kf>
				<amt_border_l>0.0</amt_border_l>
				<amt_border_r>0.0</amt_border_r>
				<amt_border_kf>-1</amt_border_kf>
			</item>
			<item>
				<tx>-18.234628</tx>
				<ty>4.465827</ty>
				<tz>-1.209684</tz>
				<rx>0.000000</rx>
				<ry>-0.000000</ry>
				<rz>3.072561</rz>
				<state>1</state>
				<occlusion>-1</occlusion>
				<occlusion_kf>-1</occlusion_kf>
				<truncation>-1</truncation>
				<amt_occlusion>0.0</amt_occlusion>
				<amt_occlusion_kf>-1</amt_occlusion_kf>
				<amt_border_l>0.0</amt_border_l>
				<amt_border_r>0.0</amt_border_r>
				<amt_border_kf>-1</amt_border_kf>
			</item>
			<item>
				<tx>-19.716493</tx>
				<ty>4.495047</ty>
				<tz>-1.233703</tz>
				<rx>0.000000</rx>
				<ry>-0.000000</ry>
				<rz>3.066136</rz>
				<state>1</state>
				<occlusion>-1</occlusion>
				<occlusion_kf>-1</occlusion_kf>
				<truncation>-1</truncation>
				<amt_occlusion>0.0</amt_occlusion>
				<amt_occlusion_kf>-1</amt_occlusion_kf>
				<amt_border_l>0.0</amt_border_l>
				<amt_border_r>0.0</amt_border_r>
				<amt_border_kf>-1</amt_border_kf>
			</item>
			<item>
				<tx>-21.209960</tx>
				<ty>4.510723</ty>
				<tz>-1.260301</tz>
				<rx>0.000000</rx>
				<ry>-0.000000</ry>
				<rz>3.067561</rz>
				<state>1</state>
				<occlusion>-1</occlusion>
				<occlusion_kf>-1</occlusion_kf>
				<truncation>-1</truncation>
				<amt_occlusion>0.0</amt_occlusion>
				<amt_occlusion_kf>-1</amt_occlusion_kf>
				<amt_border_l>0.0</amt_border_l>
				<amt_border_r>0.0</amt_border_r>
				<amt_border_kf>-1</amt_border_kf>
			</item>
			<item>
				<tx>-22.717996</tx>
				<ty>4.518224</ty>
				<tz>-1.290484</tz>
				<rx>0.000000</rx>
				<ry>-0.000000</ry>
				<rz>3.078015</rz>
				<state>1</state>
				<occlusion>-1</occlusion>
				<occlusion_kf>-1</occlusion_kf>
				<truncation>-1</truncation>
				<amt_occlusion>0.0</amt_occlusion>
				<amt_occlusion_kf>-1</amt_occlusion_kf>
				<amt_border_l>0.0</amt_border_l>
				<amt_border_r>0.0</amt_border_r>
				<amt_border_kf>-1</amt_border_kf>
			</item>
			<item>
				<tx>-24.186915</tx>
				<ty>4.506701</ty>
				<tz>-1.315231</tz>
				<rx>0.000000</rx>
				<ry>-0.000000</ry>
				<rz>3.083114</rz>
				<state>1</state>
				<occlusion>-1</occlusion>
				<occlusion_kf>-1</occlusion_kf>
				<truncation>-1</truncation>
				<amt_occlusion>0.0</amt_occlusion>
				<amt_occlusion_kf>-1</amt_occlusion_kf>
				<amt_border_l>0.0</amt_border_l>
				<amt_border_r>0.0</amt_border_r>
				<amt_border_kf>-1</amt_border_kf>
			</item>
			<item>
				<tx>-25.629082</tx>
				<ty>4.534688</ty>
				<tz>-1.335066</tz>
				<rx>0.000000</rx>
				<ry>-0.000000</ry>
				<rz>3.079913</rz>
				<state>1</state>
				<occlusion>-1</occlusion>
				<occlusion_kf>-1</occlusion_kf>
				<truncation>-1</truncation>
				<amt_occlusion>0.0</amt_occlusion>
				<amt_occlusion_kf>-1</amt_occlusion_kf>
				<amt_border_l>0.0</amt_border_l>
				<amt_border_r>0.0</amt_border_r>
				<amt_border_kf>-1</amt_border_kf>
			</item>
			<item>
				<tx>-26.918376</tx>
				<ty>4.586270</ty>
				<tz>-1.357015</tz>
				<rx>0.000000</rx>
				<ry>-0.000000</ry>
				<rz>3.075170</rz>
				<state>1</state>
				<occlusion>-1</occlusion>
				<occlusion_kf>-1</occlusion_kf>
				<truncation>-1</truncation>
				<amt_occlusion>0.0</amt_occlusion>
				<amt_occlusion_kf>-1</amt_occlusion_kf>
				<amt_border_l>0.0</amt_border_l>
				<amt_border_r>0.0</amt_border_r>
				<amt_border_kf>-1</amt_border_kf>
			</item>
			<item>
				<tx>-28.274027</tx>
				<ty>4.643405</ty>
				<tz>-1.385830</tz>
				<rx>0.000000</rx>
				<ry>-0.000000</ry>
				<rz>3.070873</rz>
				<state>1</state>
				<occlusion>-1</occlusion>
				<occlusion_kf>-1</occlusion_kf>
				<truncation>-1</truncation>
				<amt_occlusion>0.0</amt_occlusion>
				<amt_occlusion_kf>-1</amt_occlusion_kf>
				<amt_border_l>0.0</amt_border_l>
				<amt_border_r>0.0</amt_border_r>
				<amt_border_kf>-1</amt_border_kf>
			</item>
			<item>
				<tx>-30.015159</tx>
				<ty>4.683792</ty>
				<tz>-1.421996</tz>
				<rx>0.000000</rx>
				<ry>-0.000000</ry>
				<rz>3.076099</rz>
				<state>1</state>
				<occlusion>-1</occlusion>
				<occlusion_kf>-1</occlusion_kf>
				<truncation>-1</truncation>
				<amt_occlusion>0.0</amt_occlusion>
				<amt_occlusion_kf>-1</amt_occlusion_kf>
				<amt_border_l>0.0</amt_border_l>
				<amt_border_r>0.0</amt_border_r>
				<amt_border_kf>-1</amt_border_kf>
			</item>
			<item>
				<tx>-31.460162</tx>
				<ty>4.645007</ty>
				<tz>-1.443618</tz>
				<rx>0.000000</rx>
				<ry>-0.000000</ry>
				<rz>3.083934</rz>
				<state>1</state>
				<occlusion>-1</occlusion>
				<occlusion_kf>-1</occlusion_kf>
				<truncation>-1</truncation>
				<amt_occlusion>0.0</amt_occlusion>
				<amt_occlusion_kf>-1</amt_occlusion_kf>
				<amt_border_l>0.0</amt_border_l>
				<amt_border_r>0.0</amt_border_r>
				<amt_border_kf>-1</amt_border_kf>
			</item>
			<item>
				<tx>-32.896134</tx>
				<ty>4.562654</ty>
				<tz>-1.459001</tz>
				<rx>0.000000</rx>
				<ry>-0.000000</ry>
				<rz>3.083628</rz>
				<state>1</state>
				<occlusion>-1</occlusion>
				<occlusion_kf>-1</occlusion_kf>
				<truncation>-1</truncation>
				<amt_occlusion>0.0</amt_occlusion>
				<amt_occlusion_kf>-1</amt_occlusion_kf>
				<amt_border_l>0.0</amt_border_l>
				<amt_border_r>0.0</amt_border_r>
				<amt_border_kf>-1</amt_border_kf>
			</item>
			<item>
				<tx>-34.313917</tx>
				<ty>4.507291</ty>
				<tz>-1.472064</tz>
				<rx>0.000000</rx>
				<ry>-0.000000</ry>
				<rz>3.084987</rz>
				<state>1</state>
				<occlusion>-1</occlusion>
				<occlusion_kf>-1</occlusion_kf>
				<truncation>-1</truncation>
				<amt_occlusion>0.0</amt_occlusion>
				<amt_occlusion_kf>-1</amt_occlusion_kf>
				<amt_border_l>0.0</amt_border_l>
				<amt_border_r>0.0</amt_border_r>
				<amt_border_kf>-1</amt_border_kf>
			</item>
			<item>
				<tx>-35.660872</tx>
				<ty>4.495148</ty>
				<tz>-1.488620</tz>
				<rx>0.000000</rx>
				<ry>-0.000000</ry>
				<rz>3.090352</rz>
				<state>1</state>
				<occlusion>-1</occlusion>
				<occlusion_kf>-1</occlusion_kf>
				<truncation>-1</truncation>
				<amt_occlusion>0.0</amt_occlusion>
				<amt_occlusion_kf>-1</amt_occlusion_kf>
				<amt_border_l>0.0</amt_border_l>
				<amt_border_r>0.0</amt_border_r>
				<amt_border_kf>-1</amt_border_kf>
			</item>
			<item>
				<tx>-37.054123</tx>
				<ty>4.559753</ty>
				<tz>-1.516077</tz>
				<rx>0.000000</rx>
				<ry>-0.000000</ry>
				<rz>3.088282</rz>
				<state>1</state>
				<occlusion>-1</occlusion>
				<occlusion_kf>-1</occlusion_kf>
				<truncation>-1</truncation>
				<amt_occlusion>0.0</amt_occlusion>
				<amt_occlusion_kf>-1</amt_occlusion_kf>
				<amt_border_l>0.0</amt_border_l>
				<amt_border_r>0.0</amt_border_r>
				<amt_border_kf>-1</amt_border_kf>
			</item>
			<item>
				<tx>-38.505034</tx>
				<ty>4.633692</ty>
				<tz>-1.555332</tz>
				<rx>0.000000</rx>
				<ry>-0.000000</ry>
				<rz>3.077897</rz>
				<state>1</state>
				<occlusion>-1</occlusion>
				<occlusion_kf>-1</occlusion_kf>
				<truncation>-1</truncation>
				<amt_occlusion>0.0</amt_occlusion>
				<amt_occlusion_kf>-1</amt_occlusion_kf>
				<amt_border_l>0.0</amt_border_l>
				<amt_border_r>0.0</amt_border_r>
				<amt_border_kf>-1</amt_border_kf>
			</item>
			<item>
				<tx>-39.873581</tx>
				<ty>4.638594</ty>
				<tz>-1.591227</tz>
				<rx>0.000000</rx>
				<ry>-0.000000</ry>
				<rz>3.076142</rz>
				<state>1</state>
				<occlusion>-1</occlusion>
				<occlusion_kf>-1</occlusion_kf>
				<truncation>-1</truncation>
				<amt_occlusion>0.0</amt_occlusion>
				<amt_occlusion_kf>-1</amt_occlusion_kf>
				<amt_border_l>0.0</amt_border_l>
				<amt_border_r>0.0</amt_border_r>
				<amt_border_kf>-1</amt_border_kf>
			</item>
			<item>
				<tx>-41.050658</tx>
				<ty>4.624235</ty>
				<tz>-1.623902</tz>
				<rx>0.000000</rx>
				<ry>-0.000000</ry>
				<rz>3.086968</rz>
				<state>1</state>
				<occlusion>-1</occlusion>
				<occlusion_kf>-1</occlusion_kf>
				<truncation>-1</truncation>
				<amt_occlusion>0.0</amt_occlusion>
				<amt_occlusion_kf>-1</amt_occlusion_kf>
				<amt_border_l>0.0</amt_border_l>
				<amt_border_r>0.0</amt_border_r>
				<amt_border_kf>-1</amt_border_kf>
			</item>
			<item>
				<tx>-42.267830</tx>
				<ty>4.634015</ty>
				<tz>-1.652469</tz>
				<rx>0.000000</rx>
				<ry>-0.000000</ry>
				<rz>3.098614</rz>
				<state>1</state>
				<occlusion>-1</occlusion>
				<occlusion_kf>-1</occlusion_kf>
				<truncation>-1</truncation>
				<amt_occlusion>0.0</amt_occlusion>
				<amt_occlusion_kf>-1</amt_occlusion_kf>
				<amt_border_l>0.0</amt_border_l>
				<amt_border_r>0.0</amt_border_r>
				<amt_border_kf>-1</amt_border_kf>
			</item>
			<item>
				<tx>-43.895583</tx>
				<ty>4.655479</ty>
				<tz>-1.677347</tz>
				<rx>0.000000</rx>
				<ry>-0.000000</ry>
				<rz>3.096783</rz>
				<state>1</state>
				<occlusion>-1</occlusion>
				<occlusion_kf>-1</occlusion_kf>
				<truncation>-1</truncation>
				<amt_occlusion>0.0</amt_occlusion>
				<amt_occlusion_kf>-1</amt_occlusion_kf>
				<amt_border_l>0.0</amt_border_l>
				<amt_border_r>0.0</amt_border_r>
				<amt_border_kf>-1</amt_border_kf>
			</item>
			<item>
				<tx>-45.199272</tx>
				<ty>4.698487</ty>
				<tz>-1.694186</tz>
				<rx>0.000000</rx>
				<ry>-0.000000</ry>
				<rz>3.083681</rz>
				<state>1</state>
				<occlusion>-1</occlusion>
				<occlusion_kf>-1</occlusion_kf>
				<truncation>-1</truncation>
				<amt_occlusion>0.0</amt_occlusion>
				<amt_occlusion_kf>-1</amt_occlusion_kf>
				<amt_border_l>0.0</amt_border_l>
				<amt_border_r>0.0</amt_border_r>
				<amt_border_kf>-1</amt_border_kf>
			</item>
			<item>
				<tx>-46.481227</tx>
				<ty>4.749091</ty>
				<tz>-1.711263</tz>
				<rx>0.000000</rx>
				<ry>-0.000000</ry>
				<rz>3.083245</rz>
				<state>1</state>
				<occlusion>-1</occlusion>
				<occlusion_kf>-1</occlusion_kf>
				<truncation>-1</truncation>
				<amt_occlusion>0.0</amt_occlusion>
				<amt_occlusion_kf>-1</amt_occlusion_kf>
				<amt_border_l>0.0</amt_border_l>
				<amt_border_r>0.0</amt_border_r>
				<amt_border_kf>-1</amt_border_kf>
			</item>
			<item>
				<tx>-47.764001</tx>
				<ty>4.783261</ty>
				<tz>-1.730003</tz>
				<rx>0.000000</rx>
				<ry>-0.000000</ry>
				<rz>3.083431</rz>
				<state>1</state>
				<occlusion>-1</occlusion>
				<occlusion_kf>-1</occlusion_kf>
				<truncation>-1</truncation>
				<amt_occlusion>0.0</amt_occlusion>
				<amt_occlusion_kf>-1</amt_occlusion_kf>
				<amt_border_l>0.0</amt_border_l>
				<amt_border_r>0.0</amt_border_r>
				<amt_border_kf>-1</amt_border_kf>
			</item>
			<item>
				<tx>-49.029149</tx>
				<ty>4.745413</ty>
				<tz>-1.753952</tz>
				<rx>0.000000</rx>
				<ry>-0.000000</ry>
				<rz>3.090372</rz>
				<state>1</state>
				<occlusion>-1</occlusion>
				<occlusion_kf>-1</occlusion_kf>
				<truncation>-1</truncation>
				<amt_occlusion>0.0</amt_occlusion>
				<amt_occlusion_kf>-1</amt_occlusion_kf>
				<amt_border_l>0.0</amt_border_l>
				<amt_border_r>0.0</amt_border_r>
				<amt_border_kf>-1</amt_border_kf>
			</item>
			<item>
				<tx>-50.252684</tx>
				<ty>4.651564</ty>
				<tz>-1.777868</tz>
				<rx>0.000000</rx>
				<ry>-0.000000</ry>
				<rz>3.096545</rz>
				<state>1</state>
				<occlusion>-1</occlusion>
				<occlusion_kf>-1</occlusion_kf>
				<truncation>-1</truncation>
				<amt_occlusion>0.0</amt_occlusion>
				<amt_occlusion_kf>-1</amt_occlusion_kf>
				<amt_border_l>0.0</amt_border_l>
				<amt_border_r>0.0</amt_border_r>
				<amt_border_kf>-1</amt_border_kf>
			</item>
			<item>
				<tx>-51.441879</tx>
				<ty>4.635489</ty>
				<tz>-1.802478</tz>
				<rx>0.000000</rx>
				<ry>-0.000000</ry>
				<rz>3.094635</rz>
				<state>1</state>
				<occlusion>-1</occlusion>
				<occlusion_kf>-1</occlusion_kf>
				<truncation>-1</truncation>
				<amt_occlusion>0.0</amt_occlusion>
				<amt_occlusion_kf>-1</amt_occlusion_kf>
				<amt_border_l>0.0</amt_border_l>
				<amt_border_r>0.0</amt_border_r>
				<amt_border_kf>-1</amt_border_kf>
			</item>
			<item>
				<tx>-52.634840</tx>
				<ty>4.661745</ty>
				<tz>-1.827580</tz>
				<rx>0.000000</rx>
				<ry>-0.000000</ry>
				<rz>3.087173</rz>
				<state>1</state>
				<occlusion>-1</occlusion>
				<occlusion_kf>-1</occlusion_kf>
				<truncation>-1</truncation>
				<amt_occlusion>0.0</amt_occlusion>
				<amt_occlusion_kf>-1</amt_occlusion_kf>
				<amt_border_l>0.0</amt_border_l>
				<amt_border_r>0.0</amt_border_r>
				<amt_border_kf>-1</amt_border_kf>
			</item>
			<item>
				<tx>-53.657705</tx>
				<ty>4.689771</ty>
				<tz>-1.852464</tz>
				<rx>0.000000</rx>
				<ry>-0.000000</ry>
				<rz>3.078446</rz>
				<state>1</state>
				<occlusion>-1</occlusion>
				<occlusion_kf>-1</occlusion_kf>
				<truncation>-1</truncation>
				<amt_occlusion>0.0</amt_occlusion>
				<amt_occlusion_kf>-1</amt_occlusion_kf>
				<amt_border_l>0.0</amt_border_l>
				<amt_border_r>0.0</amt_border_r>
				<amt_border_kf>-1</amt_border_kf>
			</item>
			<item>
				<tx>-54.694988</tx>
				<ty>4.715660</ty>
				<tz>-1.879068</tz>
				<rx>0.000000</rx>
				<ry>-0.000000</ry>
				<rz>3.075865</rz>
				<state>1</state>
				<occlusion>-1</occlusion>
				<occlusion_kf>-1</occlusion_kf>
				<truncation>-1</truncation>
				<amt_occlusion>0.0</amt_occlusion>
				<amt_occlusion_kf>-1</amt_occlusion_kf>
				<amt_border_l>0.0</amt_border_l>
				<amt_border_r>0.0</amt_border_r>
				<amt_border_kf>-1</amt_border_kf>
			</item>
			<item>
				<tx>-56.029819</tx>
				<ty>4.741268</ty>
				<tz>-1.901207</tz>
				<rx>0.000000</rx>
				<ry>-0.000000</ry>
				<rz>3.085958</rz>
				<state>1</state>
				<occlusion>-1</occlusion>
				<occlusion_kf>-1</occlusion_kf>
				<truncation>-1</truncation>
				<amt_occlusion>0.0</amt_occlusion>
				<amt_occlusion_kf>-1</amt_occlusion_kf>
				<amt_border_l>0.0</amt_border_l>
				<amt_border_r>0.0</amt_border_r>
				<amt_border_kf>-1</amt_border_kf>
			</item>
			<item>
				<tx>-57.109401</tx>
				<ty>4.729272</ty>
				<tz>-1.916273</tz>
				<rx>0.000000</rx>
				<ry>-0.000000</ry>
				<rz>3.095841</rz>
				<state>1</state>
				<occlusion>-1</occlusion>
				<occlusion_kf>-1</occlusion_kf>
				<truncation>-1</truncation>
				<amt_occlusion>0.0</amt_occlusion>
				<amt_occlusion_kf>-1</amt_occlusion_kf>
				<amt_border_l>0.0</amt_border_l>
				<amt_border_r>0.0</amt_border_r>
				<amt_border_kf>-1</amt_border_kf>
			</item>
			<item>
				<tx>-58.136952</tx>
				<ty>4.751608</ty>
				<tz>-1.935112</tz>
				<rx>0.000000</rx>
				<ry>-0.000000</ry>
				<rz>3.092139</rz>
				<state>1</state>
				<occlusion>-1</occlusion>
				<occlusion_kf>-1</occlusion_kf>
				<truncation>-1</truncation>
				<amt_occlusion>0.0</amt_occlusion>
				<amt_occlusion_kf>-1</amt_occlusion_kf>
				<amt_border_l>0.0</amt_border_l>
				<amt_border_r>0.0</amt_border_r>
				<amt_border_kf>-1</amt_border_kf>
			</item>
			<item>
				<tx>-59.166549</tx>
				<ty>4.716625</ty>
				<tz>-1.956907</tz>
				<rx>0.000000</rx>
				<ry>-0.000000</ry>
				<rz>3.086747</rz>
				<state>1</state>
				<occlusion>-1</occlusion>
				<occlusion_kf>-1</occlusion_kf>
				<truncation>-1</truncation>
				<amt_occlusion>0.0</amt_occlusion>
				<amt_occlusion_kf>-1</amt_occlusion_kf>
				<amt_border_l>0.0</amt_border_l>
				<amt_border_r>0.0</amt_border_r>
				<amt_border_kf>-1</amt_border_kf>
			</item>
			<item>
				<tx>-60.109097</tx>
				<ty>4.713758</ty>
				<tz>-1.974113</tz>
				<rx>0.000000</rx>
				<ry>-0.000000</ry>
				<rz>3.087079</rz>
				<state>1</state>
				<occlusion>-1</occlusion>
				<occlusion_kf>-1</occlusion_kf>
				<truncation>-1</truncation>
				<amt_occlusion>0.0</amt_occlusion>
				<amt_occlusion_kf>-1</amt_occlusion_kf>
				<amt_border_l>0.0</amt_border_l>
				<amt_border_r>0.0</amt_border_r>
				<amt_border_kf>-1</amt_border_kf>
			</item>
			<item>
				<tx>-61.039348</tx>
				<ty>4.747751</ty>
				<tz>-1.990053</tz>
				<rx>0.000000</rx>
				<ry>-0.000000</ry>
				<rz>3.091307</rz>
				<state>1</state>
				<occlusion>-1</occlusion>
				<occlusion_kf>-1</occlusion_kf>
				<truncation>-1</truncation>
				<amt_occlusion>0.0</amt_occlusion>
				<amt_occlusion_kf>-1</amt_occlusion_kf>
				<amt_border_l>0.0</amt_border_l>
				<amt_border_r>0.0</amt_border_r>
				<amt_border_kf>-1</amt_border_kf>
			</item>
			<item>
				<tx>-61.850927</tx>
				<ty>4.737630</ty>
				<tz>-2.006020</tz>
				<rx>0.000000</rx>
				<ry>-0.000000</ry>
				<rz>3.094337</rz>
				<state>1</state>
				<occlusion>-1</occlusion>
				<occlusion_kf>-1</occlusion_kf>
				<truncation>-1</truncation>
				<amt_occlusion>0.0</amt_occlusion>
				<amt_occlusion_kf>-1</amt_occlusion_kf>
				<amt_border_l>0.0</amt_border_l>
				<amt_border_r>0.0</amt_border_r>
				<amt_border_kf>-1</amt_border_kf>
			</item>
			<item>
				<tx>-62.424298</tx>
				<ty>4.755183</ty>
				<tz>-2.019543</tz>
				<rx>0.000000</rx>
				<ry>-0.000000</ry>
				<rz>3.097357</rz>
				<state>1</state>
				<occlusion>-1</occlusion>
				<occlusion_kf>-1</occlusion_kf>
				<truncation>-1</truncation>
				<amt_occlusion>0.0</amt_occlusion>
				<amt_occlusion_kf>-1</amt_occlusion_kf>
				<amt_border_l>0.0</amt_border_l>
				<amt_border_r>0.0</amt_border_r>
				<amt_border_kf>-1</amt_border_kf>
			</item>
			<item>
				<tx>-62.927449</tx>
				<ty>4.771397</ty>
				<tz>-2.032113</tz>
				<rx>0.000000</rx>
				<ry>-0.000000</ry>
				<rz>3.097088</rz>
				<state>1</state>
				<occlusion>-1</occlusion>
				<occlusion_kf>-1</occlusion_kf>
				<truncation>-1</truncation>
				<amt_occlusion>0.0</amt_occlusion>
				<amt_occlusion_kf>-1</amt_occlusion_kf>
				<amt_border_l>0.0</amt_border_l>
				<amt_border_r>0.0</amt_border_r>
				<amt_border_kf>-1</amt_border_kf>
			</item>
			<item>
				<tx>-63.447434</tx>
				<ty>4.775483</ty>
				<tz>-2.045397</tz>
				<rx>0.000000</rx>
				<ry>-0.000000</ry>
				<rz>3.097036</rz>
				<state>1</state>
				<occlusion>-1</occlusion>
				<occlusion_kf>-1</occlusion_kf>
				<truncation>-1</truncation>
				<amt_occlusion>0.0</amt_occlusion>
				<amt_occlusion_kf>-1</amt_occlusion_kf>
				<amt_border_l>0.0</amt_border_l>
				<amt_border_r>0.0</amt_border_r>
				<amt_border_kf>-1</amt_border_kf>
			</item>
			<item>
				<tx>-65.366321</tx>
				<ty>4.878363</ty>
				<tz>-2.080703</tz>
				<rx>0.000000</rx>
				<ry>-0.000000</ry>
				<rz>3.086901</rz>
				<state>1</state>
				<occlusion>-1</occlusion>
				<occlusion_kf>-1</occlusion_kf>
				<truncation>-1</truncation>
				<amt_occlusion>0.0</amt_occlusion>
				<amt_occlusion_kf>-1</amt_occlusion_kf>
				<amt_border_l>0.0</amt_border_l>
				<amt_border_r>0.0</amt_border_r>
				<amt_border_kf>-1</amt_border_kf>
			</item>
			<item>
				<tx>-66.301855</tx>
				<ty>4.905185</ty>
				<tz>-2.100637</tz>
				<rx>0.000000</rx>
				<ry>-0.000000</ry>
				<rz>3.090430</rz>
				<state>1</state>
				<occlusion>-1</occlusion>
				<occlusion_kf>-1</occlusion_kf>
				<truncation>-1</truncation>
				<amt_occlusion>0.0</amt_occlusion>
				<amt_occlusion_kf>-1</amt_occlusion_kf>
				<amt_border_l>0.0</amt_border_l>
				<amt_border_r>0.0</amt_border_r>
				<amt_border_kf>-1</amt_border_kf>
			</item>
			<item>
				<tx>-67.065352</tx>
				<ty>4.962460</ty>
				<tz>-2.115565</tz>
				<rx>0.000000</rx>
				<ry>-0.000000</ry>
				<rz>3.091772</rz>
				<state>1</state>
				<occlusion>-1</occlusion>
				<occlusion_kf>-1</occlusion_kf>
				<truncation>-1</truncation>
				<amt_occlusion>0.0</amt_occlusion>
				<amt_occlusion_kf>-1</amt_occlusion_kf>
				<amt_border_l>0.0</amt_border_l>
				<amt_border_r>0.0</amt_border_r>
				<amt_border_kf>-1</amt_border_kf>
			</item>
			<item>
				<tx>-67.788583</tx>
				<ty>5.049182</ty>
				<tz>-2.127205</tz>
				<rx>0.000000</rx>
				<ry>-0.000000</ry>
				<rz>3.090704</rz>
				<state>1</state>
				<occlusion>-1</occlusion>
				<occlusion_kf>-1</occlusion_kf>
				<truncation>-1</truncation>
				<amt_occlusion>0.0</amt_occlusion>
				<amt_occlusion_kf>-1</amt_occlusion_kf>
				<amt_border_l>0.0</amt_border_l>
				<amt_border_r>0.0</amt_border_r>
				<amt_border_kf>-1</amt_border_kf>
			</item>
			<item>
				<tx>-68.478896</tx>
				<ty>5.104517</ty>
				<tz>-2.138383</tz>
				<rx>0.000000</rx>
				<ry>-0.000000</ry>
				<rz>3.092918</rz>
				<state>1</state>
				<occlusion>-1</occlusion>
				<occlusion_kf>-1</occlusion_kf>
				<truncation>-1</truncation>
				<amt_occlusion>0.0</amt_occlusion>
				<amt_occlusion_kf>-1</amt_occlusion_kf>
				<amt_border_l>0.0</amt_border_l>
				<amt_border_r>0.0</amt_border_r>
				<amt_border_kf>-1</amt_border_kf>
			</item>
			<item>
				<tx>-69.164564</tx>
				<ty>5.111316</ty>
				<tz>-2.149771</tz>
				<rx>0.000000</rx>
				<ry>-0.000000</ry>
				<rz>3.097234</rz>
				<state>1</state>
				<occlusion>-1</occlusion>
				<occlusion_kf>-1</occlusion_kf>
				<truncation>-1</truncation>
				<amt_occlusion>0.0</amt_occlusion>
				<amt_occlusion_kf>-1</amt_occlusion_kf>
				<amt_border_l>0.0</amt_border_l>
				<amt_border_r>0.0</amt_border_r>
				<amt_border_kf>-1</amt_border_kf>
			</item>
			<item>
				<tx>-69.825327</tx>
				<ty>5.074130</ty>
				<tz>-2.162030</tz>
				<rx>0.000000</rx>
				<ry>-0.000000</ry>
				<rz>3.097605</rz>
				<state>1</state>
				<occlusion>-1</occlusion>
				<occlusion_kf>-1</occlusion_kf>
				<truncation>-1</truncation>
				<amt_occlusion>0.0</amt_occlusion>
				<amt_occlusion_kf>-1</amt_occlusion_kf>
				<amt_border_l>0.0</amt_border_l>
				<amt_border_r>0.0</amt_border_r>
				<amt_border_kf>-1</amt_border_kf>
			</item>
			<item>
				<tx>-70.453578</tx>
				<ty>5.029658</ty>
				<tz>-2.177103</tz>
				<rx>0.000000</rx>
				<ry>-0.000000</ry>
				<rz>3.095849</rz>
				<state>1</state>
				<occlusion>-1</occlusion>
				<occlusion_kf>-1</occlusion_kf>
				<truncation>-1</truncation>
				<amt_occlusion>0.0</amt_occlusion>
				<amt_occlusion_kf>-1</amt_occlusion_kf>
				<amt_border_l>0.0</amt_border_l>
				<amt_border_r>0.0</amt_border_r>
				<amt_border_kf>-1</amt_border_kf>
			</item>
			<item>
				<tx>-70.942014</tx>
				<ty>5.015511</ty>
				<tz>-2.188214</tz>
				<rx>0.000000</rx>
				<ry>-0.000000</ry>
				<rz>3.092748</rz>
				<state>1</state>
				<occlusion>-1</occlusion>
				<occlusion_kf>-1</occlusion_kf>
				<truncation>-1</truncation>
				<amt_occlusion>0.0</amt_occlusion>
				<amt_occlusion_kf>-1</amt_occlusion_kf>
				<amt_border_l>0.0</amt_border_l>
				<amt_border_r>0.0</amt_border_r>
				<amt_border_kf>-1</amt_border_kf>
			</item>
			<item>
				<tx>-71.373424</tx>
				<ty>4.958137</ty>
				<tz>-2.195792</tz>
				<rx>0.000000</rx>
				<ry>-0.000000</ry>
				<rz>3.089096</rz>
				<state>1</state>
				<occlusion>-1</occlusion>
				<occlusion_kf>-1</occlusion_kf>
				<truncation>-1</truncation>
				<amt_occlusion>0.0</amt_occlusion>
				<amt_occlusion_kf>-1</amt_occlusion_kf>
				<amt_border_l>0.0</amt_border_l>
				<amt_border_r>0.0</amt_border_r>
				<amt_border_kf>-1</amt_border_kf>
			</item>
			<item>
				<tx>-72.190081</tx>
				<ty>4.853959</ty>
				<tz>-2.206840</tz>
				<rx>0.000000</rx>
				<ry>-0.000000</ry>
				<rz>3.084055</rz>
				<state>1</state>
				<occlusion>-1</occlusion>
				<occlusion_kf>-1</occlusion_kf>
				<truncation>-1</truncation>
				<amt_occlusion>0.0</amt_occlusion>
				<amt_occlusion_kf>-1</amt_occlusion_kf>
				<amt_border_l>0.0</amt_border_l>
				<amt_border_r>0.0</amt_border_r>
				<amt_border_kf>-1</amt_border_kf>
			</item>
			<item>
				<tx>-72.716738</tx>
				<ty>4.891880</ty>
				<tz>-2.214823</tz>
				<rx>0.000000</rx>
				<ry>-0.000000</ry>
				<rz>3.090854</rz>
				<state>1</state>
				<occlusion>-1</occlusion>
				<occlusion_kf>-1</occlusion_kf>
				<truncation>-1</truncation>
				<amt_occlusion>0.0</amt_occlusion>
				<amt_occlusion_kf>-1</amt_occlusion_kf>
				<amt_border_l>0.0</amt_border_l>
				<amt_border_r>0.0</amt_border_r>
				<amt_border_kf>-1</amt_border_kf>
			</item>
		</poses>
		<finished>1</finished>
	</item>
</tracklets>
</boost_serialization> 
