<?xml version="1.0" encoding="UTF-8" standalone="yes" ?>
<!DOCTYPE boost_serialization>
<boost_serialization signature="serialization::archive" version="9">
<tracklets class_id="0" tracking_level="0" version="0">
	<count>1</count>
	<item_version>1</item_version> 
	<item class_id="1" tracking_level="0" version="1">
		<objectType>Car</objectType>
		<h>1.574800</h>
		<w>1.447800</w>
		<l>4.241800</l>
		<first_frame>0</first_frame>
		<poses class_id="2" tracking_level="0" version="0">
			<count>47</count>
			<item_version>2</item_version>
			<item class_id="3" tracking_level="0" version="2">
				<tx>10.023942</tx>
				<ty>0.127031</ty>
				<tz>-0.671000</tz>
				<rx>0.000000</rx>
				<ry>-0.000000</ry>
				<rz>0.005183</rz>
				<state>1</state>
				<occlusion>-1</occlusion>
				<occlusion_kf>-1</occlusion_kf>
				<truncation>-1</truncation>
				<amt_occlusion>0.0</amt_occlusion>
				<amt_occlusion_kf>-1</amt_occlusion_kf>
				<amt_border_l>0.0</amt_border_l>
				<amt_border_r>0.0</amt_border_r>
				<amt_border_kf>-1</amt_border_kf>
			</item>
			<item>
				<tx>10.135556</tx>
				<ty>0.137828</ty>
				<tz>-0.668536</tz>
				<rx>0.000000</rx>
				<ry>-0.000000</ry>
				<rz>0.006093</rz>
				<state>1</state>
				<occlusion>-1</occlusion>
				<occlusion_kf>-1</occlusion_kf>
				<truncation>-1</truncation>
				<amt_occlusion>0.0</amt_occlusion>
				<amt_occlusion_kf>-1</amt_occlusion_kf>
				<amt_border_l>0.0</amt_border_l>
				<amt_border_r>0.0</amt_border_r>
				<amt_border_kf>-1</amt_border_kf>
			</item>
			<item>
				<tx>10.231502</tx>
				<ty>0.137026</ty>
				<tz>-0.666776</tz>
				<rx>0.000000</rx>
				<ry>-0.000000</ry>
				<rz>-0.000557</rz>
				<state>1</state>
				<occlusion>-1</occlusion>
				<occlusion_kf>-1</occlusion_kf>
				<truncation>-1</truncation>
				<amt_occlusion>0.0</amt_occlusion>
				<amt_occlusion_kf>-1</amt_occlusion_kf>
				<amt_border_l>0.0</amt_border_l>
				<amt_border_r>0.0</amt_border_r>
				<amt_border_kf>-1</amt_border_kf>
			</item>
			<item>
				<tx>10.370732</tx>
				<ty>0.141608</ty>
				<tz>-0.668854</tz>
				<rx>0.000000</rx>
				<ry>-0.000000</ry>
				<rz>0.008993</rz>
				<state>1</state>
				<occlusion>-1</occlusion>
				<occlusion_kf>-1</occlusion_kf>
				<truncation>-1</truncation>
				<amt_occlusion>0.0</amt_occlusion>
				<amt_occlusion_kf>-1</amt_occlusion_kf>
				<amt_border_l>0.0</amt_border_l>
				<amt_border_r>0.0</amt_border_r>
				<amt_border_kf>-1</amt_border_kf>
			</item>
			<item>
				<tx>10.516741</tx>
				<ty>0.137042</ty>
				<tz>-0.670048</tz>
				<rx>0.000000</rx>
				<ry>-0.000000</ry>
				<rz>0.004649</rz>
				<state>1</state>
				<occlusion>-1</occlusion>
				<occlusion_kf>-1</occlusion_kf>
				<truncation>-1</truncation>
				<amt_occlusion>0.0</amt_occlusion>
				<amt_occlusion_kf>-1</amt_occlusion_kf>
				<amt_border_l>0.0</amt_border_l>
				<amt_border_r>0.0</amt_border_r>
				<amt_border_kf>-1</amt_border_kf>
			</item>
			<item>
				<tx>10.662024</tx>
				<ty>0.127487</ty>
				<tz>-0.666861</tz>
				<rx>0.000000</rx>
				<ry>-0.000000</ry>
				<rz>-0.006249</rz>
				<state>1</state>
				<occlusion>-1</occlusion>
				<occlusion_kf>-1</occlusion_kf>
				<truncation>-1</truncation>
				<amt_occlusion>0.0</amt_occlusion>
				<amt_occlusion_kf>-1</amt_occlusion_kf>
				<amt_border_l>0.0</amt_border_l>
				<amt_border_r>0.0</amt_border_r>
				<amt_border_kf>-1</amt_border_kf>
			</item>
			<item>
				<tx>10.809840</tx>
				<ty>0.131262</ty>
				<tz>-0.666794</tz>
				<rx>0.000000</rx>
				<ry>-0.000000</ry>
				<rz>0.001975</rz>
				<state>1</state>
				<occlusion>-1</occlusion>
				<occlusion_kf>-1</occlusion_kf>
				<truncation>-1</truncation>
				<amt_occlusion>0.0</amt_occlusion>
				<amt_occlusion_kf>-1</amt_occlusion_kf>
				<amt_border_l>0.0</amt_border_l>
				<amt_border_r>0.0</amt_border_r>
				<amt_border_kf>-1</amt_border_kf>
			</item>
			<item>
				<tx>10.959405</tx>
				<ty>0.145561</ty>
				<tz>-0.668552</tz>
				<rx>0.000000</rx>
				<ry>-0.000000</ry>
				<rz>0.002103</rz>
				<state>1</state>
				<occlusion>-1</occlusion>
				<occlusion_kf>-1</occlusion_kf>
				<truncation>-1</truncation>
				<amt_occlusion>0.0</amt_occlusion>
				<amt_occlusion_kf>-1</amt_occlusion_kf>
				<amt_border_l>0.0</amt_border_l>
				<amt_border_r>0.0</amt_border_r>
				<amt_border_kf>-1</amt_border_kf>
			</item>
			<item>
				<tx>11.116995</tx>
				<ty>0.146081</ty>
				<tz>-0.670587</tz>
				<rx>0.000000</rx>
				<ry>-0.000000</ry>
				<rz>-0.005230</rz>
				<state>1</state>
				<occlusion>-1</occlusion>
				<occlusion_kf>-1</occlusion_kf>
				<truncation>-1</truncation>
				<amt_occlusion>0.0</amt_occlusion>
				<amt_occlusion_kf>-1</amt_occlusion_kf>
				<amt_border_l>0.0</amt_border_l>
				<amt_border_r>0.0</amt_border_r>
				<amt_border_kf>-1</amt_border_kf>
			</item>
			<item>
				<tx>11.264865</tx>
				<ty>0.139912</ty>
				<tz>-0.673477</tz>
				<rx>0.000000</rx>
				<ry>-0.000000</ry>
				<rz>0.006144</rz>
				<state>1</state>
				<occlusion>-1</occlusion>
				<occlusion_kf>-1</occlusion_kf>
				<truncation>-1</truncation>
				<amt_occlusion>0.0</amt_occlusion>
				<amt_occlusion_kf>-1</amt_occlusion_kf>
				<amt_border_l>0.0</amt_border_l>
				<amt_border_r>0.0</amt_border_r>
				<amt_border_kf>-1</amt_border_kf>
			</item>
			<item>
				<tx>11.414478</tx>
				<ty>0.160309</ty>
				<tz>-0.677993</tz>
				<rx>0.000000</rx>
				<ry>-0.000000</ry>
				<rz>0.017819</rz>
				<state>1</state>
				<occlusion>-1</occlusion>
				<occlusion_kf>-1</occlusion_kf>
				<truncation>-1</truncation>
				<amt_occlusion>0.0</amt_occlusion>
				<amt_occlusion_kf>-1</amt_occlusion_kf>
				<amt_border_l>0.0</amt_border_l>
				<amt_border_r>0.0</amt_border_r>
				<amt_border_kf>-1</amt_border_kf>
			</item>
			<item>
				<tx>11.538114</tx>
				<ty>0.170620</ty>
				<tz>-0.679000</tz>
				<rx>0.000000</rx>
				<ry>-0.000000</ry>
				<rz>0.025037</rz>
				<state>1</state>
				<occlusion>-1</occlusion>
				<occlusion_kf>-1</occlusion_kf>
				<truncation>-1</truncation>
				<amt_occlusion>0.0</amt_occlusion>
				<amt_occlusion_kf>-1</amt_occlusion_kf>
				<amt_border_l>0.0</amt_border_l>
				<amt_border_r>0.0</amt_border_r>
				<amt_border_kf>-1</amt_border_kf>
			</item>
			<item>
				<tx>11.648550</tx>
				<ty>0.174184</ty>
				<tz>-0.682754</tz>
				<rx>0.000000</rx>
				<ry>-0.000000</ry>
				<rz>0.011891</rz>
				<state>1</state>
				<occlusion>-1</occlusion>
				<occlusion_kf>-1</occlusion_kf>
				<truncation>-1</truncation>
				<amt_occlusion>0.0</amt_occlusion>
				<amt_occlusion_kf>-1</amt_occlusion_kf>
				<amt_border_l>0.0</amt_border_l>
				<amt_border_r>0.0</amt_border_r>
				<amt_border_kf>-1</amt_border_kf>
			</item>
			<item>
				<tx>11.808022</tx>
				<ty>0.182763</ty>
				<tz>-0.686180</tz>
				<rx>0.000000</rx>
				<ry>-0.000000</ry>
				<rz>0.004791</rz>
				<state>1</state>
				<occlusion>-1</occlusion>
				<occlusion_kf>-1</occlusion_kf>
				<truncation>-1</truncation>
				<amt_occlusion>0.0</amt_occlusion>
				<amt_occlusion_kf>-1</amt_occlusion_kf>
				<amt_border_l>0.0</amt_border_l>
				<amt_border_r>0.0</amt_border_r>
				<amt_border_kf>-1</amt_border_kf>
			</item>
			<item>
				<tx>11.900027</tx>
				<ty>0.179820</ty>
				<tz>-0.686260</tz>
				<rx>0.000000</rx>
				<ry>-0.000000</ry>
				<rz>0.003377</rz>
				<state>1</state>
				<occlusion>-1</occlusion>
				<occlusion_kf>-1</occlusion_kf>
				<truncation>-1</truncation>
				<amt_occlusion>0.0</amt_occlusion>
				<amt_occlusion_kf>-1</amt_occlusion_kf>
				<amt_border_l>0.0</amt_border_l>
				<amt_border_r>0.0</amt_border_r>
				<amt_border_kf>-1</amt_border_kf>
			</item>
			<item>
				<tx>11.950645</tx>
				<ty>0.195019</ty>
				<tz>-0.689939</tz>
				<rx>0.000000</rx>
				<ry>-0.000000</ry>
				<rz>0.012137</rz>
				<state>1</state>
				<occlusion>-1</occlusion>
				<occlusion_kf>-1</occlusion_kf>
				<truncation>-1</truncation>
				<amt_occlusion>0.0</amt_occlusion>
				<amt_occlusion_kf>-1</amt_occlusion_kf>
				<amt_border_l>0.0</amt_border_l>
				<amt_border_r>0.0</amt_border_r>
				<amt_border_kf>-1</amt_border_kf>
			</item>
			<item>
				<tx>12.051050</tx>
				<ty>0.201564</ty>
				<tz>-0.691329</tz>
				<rx>0.000000</rx>
				<ry>-0.000000</ry>
				<rz>0.021185</rz>
				<state>1</state>
				<occlusion>-1</occlusion>
				<occlusion_kf>-1</occlusion_kf>
				<truncation>-1</truncation>
				<amt_occlusion>0.0</amt_occlusion>
				<amt_occlusion_kf>-1</amt_occlusion_kf>
				<amt_border_l>0.0</amt_border_l>
				<amt_border_r>0.0</amt_border_r>
				<amt_border_kf>-1</amt_border_kf>
			</item>
			<item>
				<tx>12.145727</tx>
				<ty>0.221897</ty>
				<tz>-0.694910</tz>
				<rx>0.000000</rx>
				<ry>-0.000000</ry>
				<rz>0.022286</rz>
				<state>1</state>
				<occlusion>-1</occlusion>
				<occlusion_kf>-1</occlusion_kf>
				<truncation>-1</truncation>
				<amt_occlusion>0.0</amt_occlusion>
				<amt_occlusion_kf>-1</amt_occlusion_kf>
				<amt_border_l>0.0</amt_border_l>
				<amt_border_r>0.0</amt_border_r>
				<amt_border_kf>-1</amt_border_kf>
			</item>
			<item>
				<tx>12.216728</tx>
				<ty>0.221244</ty>
				<tz>-0.692858</tz>
				<rx>0.000000</rx>
				<ry>-0.000000</ry>
				<rz>0.013145</rz>
				<state>1</state>
				<occlusion>-1</occlusion>
				<occlusion_kf>-1</occlusion_kf>
				<truncation>-1</truncation>
				<amt_occlusion>0.0</amt_occlusion>
				<amt_occlusion_kf>-1</amt_occlusion_kf>
				<amt_border_l>0.0</amt_border_l>
				<amt_border_r>0.0</amt_border_r>
				<amt_border_kf>-1</amt_border_kf>
			</item>
			<item>
				<tx>12.279494</tx>
				<ty>0.217801</ty>
				<tz>-0.695890</tz>
				<rx>0.000000</rx>
				<ry>-0.000000</ry>
				<rz>0.007989</rz>
				<state>1</state>
				<occlusion>-1</occlusion>
				<occlusion_kf>-1</occlusion_kf>
				<truncation>-1</truncation>
				<amt_occlusion>0.0</amt_occlusion>
				<amt_occlusion_kf>-1</amt_occlusion_kf>
				<amt_border_l>0.0</amt_border_l>
				<amt_border_r>0.0</amt_border_r>
				<amt_border_kf>-1</amt_border_kf>
			</item>
			<item>
				<tx>12.346570</tx>
				<ty>0.216944</ty>
				<tz>-0.697812</tz>
				<rx>0.000000</rx>
				<ry>-0.000000</ry>
				<rz>0.004638</rz>
				<state>1</state>
				<occlusion>-1</occlusion>
				<occlusion_kf>-1</occlusion_kf>
				<truncation>-1</truncation>
				<amt_occlusion>0.0</amt_occlusion>
				<amt_occlusion_kf>-1</amt_occlusion_kf>
				<amt_border_l>0.0</amt_border_l>
				<amt_border_r>0.0</amt_border_r>
				<amt_border_kf>-1</amt_border_kf>
			</item>
			<item>
				<tx>12.401720</tx>
				<ty>0.210920</ty>
				<tz>-0.705303</tz>
				<rx>0.000000</rx>
				<ry>-0.000000</ry>
				<rz>0.006721</rz>
				<state>1</state>
				<occlusion>-1</occlusion>
				<occlusion_kf>-1</occlusion_kf>
				<truncation>-1</truncation>
				<amt_occlusion>0.0</amt_occlusion>
				<amt_occlusion_kf>-1</amt_occlusion_kf>
				<amt_border_l>0.0</amt_border_l>
				<amt_border_r>0.0</amt_border_r>
				<amt_border_kf>-1</amt_border_kf>
			</item>
			<item>
				<tx>12.287585</tx>
				<ty>0.209366</ty>
				<tz>-0.711289</tz>
				<rx>0.000000</rx>
				<ry>-0.000000</ry>
				<rz>0.011457</rz>
				<state>1</state>
				<occlusion>-1</occlusion>
				<occlusion_kf>-1</occlusion_kf>
				<truncation>-1</truncation>
				<amt_occlusion>0.0</amt_occlusion>
				<amt_occlusion_kf>-1</amt_occlusion_kf>
				<amt_border_l>0.0</amt_border_l>
				<amt_border_r>0.0</amt_border_r>
				<amt_border_kf>-1</amt_border_kf>
			</item>
			<item>
				<tx>12.041366</tx>
				<ty>0.180150</ty>
				<tz>-0.713408</tz>
				<rx>0.000000</rx>
				<ry>-0.000000</ry>
				<rz>0.012554</rz>
				<state>1</state>
				<occlusion>-1</occlusion>
				<occlusion_kf>-1</occlusion_kf>
				<truncation>-1</truncation>
				<amt_occlusion>0.0</amt_occlusion>
				<amt_occlusion_kf>-1</amt_occlusion_kf>
				<amt_border_l>0.0</amt_border_l>
				<amt_border_r>0.0</amt_border_r>
				<amt_border_kf>-1</amt_border_kf>
			</item>
			<item>
				<tx>11.747448</tx>
				<ty>0.165039</ty>
				<tz>-0.713658</tz>
				<rx>0.000000</rx>
				<ry>-0.000000</ry>
				<rz>0.011543</rz>
				<state>1</state>
				<occlusion>-1</occlusion>
				<occlusion_kf>-1</occlusion_kf>
				<truncation>-1</truncation>
				<amt_occlusion>0.0</amt_occlusion>
				<amt_occlusion_kf>-1</amt_occlusion_kf>
				<amt_border_l>0.0</amt_border_l>
				<amt_border_r>0.0</amt_border_r>
				<amt_border_kf>-1</amt_border_kf>
			</item>
			<item>
				<tx>12.574808</tx>
				<ty>0.175996</ty>
				<tz>-0.721397</tz>
				<rx>0.000000</rx>
				<ry>-0.000000</ry>
				<rz>0.024968</rz>
				<state>1</state>
				<occlusion>-1</occlusion>
				<occlusion_kf>-1</occlusion_kf>
				<truncation>-1</truncation>
				<amt_occlusion>0.0</amt_occlusion>
				<amt_occlusion_kf>-1</amt_occlusion_kf>
				<amt_border_l>0.0</amt_border_l>
				<amt_border_r>0.0</amt_border_r>
				<amt_border_kf>-1</amt_border_kf>
			</item>
			<item>
				<tx>12.676822</tx>
				<ty>0.158232</ty>
				<tz>-0.727633</tz>
				<rx>0.000000</rx>
				<ry>-0.000000</ry>
				<rz>-0.006391</rz>
				<state>1</state>
				<occlusion>-1</occlusion>
				<occlusion_kf>-1</occlusion_kf>
				<truncation>-1</truncation>
				<amt_occlusion>0.0</amt_occlusion>
				<amt_occlusion_kf>-1</amt_occlusion_kf>
				<amt_border_l>0.0</amt_border_l>
				<amt_border_r>0.0</amt_border_r>
				<amt_border_kf>-1</amt_border_kf>
			</item>
			<item>
				<tx>12.721675</tx>
				<ty>0.120468</ty>
				<tz>-0.731414</tz>
				<rx>0.000000</rx>
				<ry>-0.000000</ry>
				<rz>-0.024758</rz>
				<state>1</state>
				<occlusion>-1</occlusion>
				<occlusion_kf>-1</occlusion_kf>
				<truncation>-1</truncation>
				<amt_occlusion>0.0</amt_occlusion>
				<amt_occlusion_kf>-1</amt_occlusion_kf>
				<amt_border_l>0.0</amt_border_l>
				<amt_border_r>0.0</amt_border_r>
				<amt_border_kf>-1</amt_border_kf>
			</item>
			<item>
				<tx>12.772052</tx>
				<ty>0.104612</ty>
				<tz>-0.737577</tz>
				<rx>0.000000</rx>
				<ry>-0.000000</ry>
				<rz>-0.022422</rz>
				<state>1</state>
				<occlusion>-1</occlusion>
				<occlusion_kf>-1</occlusion_kf>
				<truncation>-1</truncation>
				<amt_occlusion>0.0</amt_occlusion>
				<amt_occlusion_kf>-1</amt_occlusion_kf>
				<amt_border_l>0.0</amt_border_l>
				<amt_border_r>0.0</amt_border_r>
				<amt_border_kf>-1</amt_border_kf>
			</item>
			<item>
				<tx>12.827758</tx>
				<ty>0.100098</ty>
				<tz>-0.738995</tz>
				<rx>0.000000</rx>
				<ry>-0.000000</ry>
				<rz>-0.002924</rz>
				<state>1</state>
				<occlusion>-1</occlusion>
				<occlusion_kf>-1</occlusion_kf>
				<truncation>-1</truncation>
				<amt_occlusion>0.0</amt_occlusion>
				<amt_occlusion_kf>-1</amt_occlusion_kf>
				<amt_border_l>0.0</amt_border_l>
				<amt_border_r>0.0</amt_border_r>
				<amt_border_kf>-1</amt_border_kf>
			</item>
			<item>
				<tx>12.902210</tx>
				<ty>0.079104</ty>
				<tz>-0.746346</tz>
				<rx>0.000000</rx>
				<ry>-0.000000</ry>
				<rz>0.018457</rz>
				<state>1</state>
				<occlusion>-1</occlusion>
				<occlusion_kf>-1</occlusion_kf>
				<truncation>-1</truncation>
				<amt_occlusion>0.0</amt_occlusion>
				<amt_occlusion_kf>-1</amt_occlusion_kf>
				<amt_border_l>0.0</amt_border_l>
				<amt_border_r>0.0</amt_border_r>
				<amt_border_kf>-1</amt_border_kf>
			</item>
			<item>
				<tx>12.968390</tx>
				<ty>0.057750</ty>
				<tz>-0.752910</tz>
				<rx>0.000000</rx>
				<ry>-0.000000</ry>
				<rz>0.014964</rz>
				<state>1</state>
				<occlusion>-1</occlusion>
				<occlusion_kf>-1</occlusion_kf>
				<truncation>-1</truncation>
				<amt_occlusion>0.0</amt_occlusion>
				<amt_occlusion_kf>-1</amt_occlusion_kf>
				<amt_border_l>0.0</amt_border_l>
				<amt_border_r>0.0</amt_border_r>
				<amt_border_kf>-1</amt_border_kf>
			</item>
			<item>
				<tx>13.024184</tx>
				<ty>0.054085</ty>
				<tz>-0.759195</tz>
				<rx>0.000000</rx>
				<ry>-0.000000</ry>
				<rz>0.001418</rz>
				<state>1</state>
				<occlusion>-1</occlusion>
				<occlusion_kf>-1</occlusion_kf>
				<truncation>-1</truncation>
				<amt_occlusion>0.0</amt_occlusion>
				<amt_occlusion_kf>-1</amt_occlusion_kf>
				<amt_border_l>0.0</amt_border_l>
				<amt_border_r>0.0</amt_border_r>
				<amt_border_kf>-1</amt_border_kf>
			</item>
			<item>
				<tx>13.134043</tx>
				<ty>0.058810</ty>
				<tz>-0.762539</tz>
				<rx>0.000000</rx>
				<ry>-0.000000</ry>
				<rz>-0.011168</rz>
				<state>1</state>
				<occlusion>-1</occlusion>
				<occlusion_kf>-1</occlusion_kf>
				<truncation>-1</truncation>
				<amt_occlusion>0.0</amt_occlusion>
				<amt_occlusion_kf>-1</amt_occlusion_kf>
				<amt_border_l>0.0</amt_border_l>
				<amt_border_r>0.0</amt_border_r>
				<amt_border_kf>-1</amt_border_kf>
			</item>
			<item>
				<tx>13.190693</tx>
				<ty>0.043365</ty>
				<tz>-0.764453</tz>
				<rx>0.000000</rx>
				<ry>-0.000000</ry>
				<rz>-0.022835</rz>
				<state>1</state>
				<occlusion>-1</occlusion>
				<occlusion_kf>-1</occlusion_kf>
				<truncation>-1</truncation>
				<amt_occlusion>0.0</amt_occlusion>
				<amt_occlusion_kf>-1</amt_occlusion_kf>
				<amt_border_l>0.0</amt_border_l>
				<amt_border_r>0.0</amt_border_r>
				<amt_border_kf>-1</amt_border_kf>
			</item>
			<item>
				<tx>13.242359</tx>
				<ty>0.033465</ty>
				<tz>-0.766801</tz>
				<rx>0.000000</rx>
				<ry>-0.000000</ry>
				<rz>-0.015619</rz>
				<state>1</state>
				<occlusion>-1</occlusion>
				<occlusion_kf>-1</occlusion_kf>
				<truncation>-1</truncation>
				<amt_occlusion>0.0</amt_occlusion>
				<amt_occlusion_kf>-1</amt_occlusion_kf>
				<amt_border_l>0.0</amt_border_l>
				<amt_border_r>0.0</amt_border_r>
				<amt_border_kf>-1</amt_border_kf>
			</item>
			<item>
				<tx>13.339645</tx>
				<ty>0.006110</ty>
				<tz>-0.772881</tz>
				<rx>0.000000</rx>
				<ry>-0.000000</ry>
				<rz>-0.005466</rz>
				<state>1</state>
				<occlusion>-1</occlusion>
				<occlusion_kf>-1</occlusion_kf>
				<truncation>-1</truncation>
				<amt_occlusion>0.0</amt_occlusion>
				<amt_occlusion_kf>-1</amt_occlusion_kf>
				<amt_border_l>0.0</amt_border_l>
				<amt_border_r>0.0</amt_border_r>
				<amt_border_kf>-1</amt_border_kf>
			</item>
			<item>
				<tx>13.446122</tx>
				<ty>-0.022579</ty>
				<tz>-0.778200</tz>
				<rx>0.000000</rx>
				<ry>-0.000000</ry>
				<rz>-0.000074</rz>
				<state>1</state>
				<occlusion>-1</occlusion>
				<occlusion_kf>-1</occlusion_kf>
				<truncation>-1</truncation>
				<amt_occlusion>0.0</amt_occlusion>
				<amt_occlusion_kf>-1</amt_occlusion_kf>
				<amt_border_l>0.0</amt_border_l>
				<amt_border_r>0.0</amt_border_r>
				<amt_border_kf>-1</amt_border_kf>
			</item>
			<item>
				<tx>13.550357</tx>
				<ty>-0.026590</ty>
				<tz>-0.789706</tz>
				<rx>0.000000</rx>
				<ry>-0.000000</ry>
				<rz>0.000064</rz>
				<state>1</state>
				<occlusion>-1</occlusion>
				<occlusion_kf>-1</occlusion_kf>
				<truncation>-1</truncation>
				<amt_occlusion>0.0</amt_occlusion>
				<amt_occlusion_kf>-1</amt_occlusion_kf>
				<amt_border_l>0.0</amt_border_l>
				<amt_border_r>0.0</amt_border_r>
				<amt_border_kf>-1</amt_border_kf>
			</item>
			<item>
				<tx>13.650331</tx>
				<ty>-0.032454</ty>
				<tz>-0.796996</tz>
				<rx>0.000000</rx>
				<ry>-0.000000</ry>
				<rz>-0.004458</rz>
				<state>1</state>
				<occlusion>-1</occlusion>
				<occlusion_kf>-1</occlusion_kf>
				<truncation>-1</truncation>
				<amt_occlusion>0.0</amt_occlusion>
				<amt_occlusion_kf>-1</amt_occlusion_kf>
				<amt_border_l>0.0</amt_border_l>
				<amt_border_r>0.0</amt_border_r>
				<amt_border_kf>-1</amt_border_kf>
			</item>
			<item>
				<tx>13.746287</tx>
				<ty>0.011045</ty>
				<tz>-0.804544</tz>
				<rx>0.000000</rx>
				<ry>-0.000000</ry>
				<rz>-0.003162</rz>
				<state>1</state>
				<occlusion>-1</occlusion>
				<occlusion_kf>-1</occlusion_kf>
				<truncation>-1</truncation>
				<amt_occlusion>0.0</amt_occlusion>
				<amt_occlusion_kf>-1</amt_occlusion_kf>
				<amt_border_l>0.0</amt_border_l>
				<amt_border_r>0.0</amt_border_r>
				<amt_border_kf>-1</amt_border_kf>
			</item>
			<item>
				<tx>13.851523</tx>
				<ty>0.023671</ty>
				<tz>-0.809264</tz>
				<rx>0.000000</rx>
				<ry>-0.000000</ry>
				<rz>-0.010085</rz>
				<state>1</state>
				<occlusion>-1</occlusion>
				<occlusion_kf>-1</occlusion_kf>
				<truncation>-1</truncation>
				<amt_occlusion>0.0</amt_occlusion>
				<amt_occlusion_kf>-1</amt_occlusion_kf>
				<amt_border_l>0.0</amt_border_l>
				<amt_border_r>0.0</amt_border_r>
				<amt_border_kf>-1</amt_border_kf>
			</item>
			<item>
				<tx>13.709823</tx>
				<ty>0.029382</ty>
				<tz>-0.809331</tz>
				<rx>0.000000</rx>
				<ry>-0.000000</ry>
				<rz>-0.010486</rz>
				<state>1</state>
				<occlusion>-1</occlusion>
				<occlusion_kf>-1</occlusion_kf>
				<truncation>-1</truncation>
				<amt_occlusion>0.0</amt_occlusion>
				<amt_occlusion_kf>-1</amt_occlusion_kf>
				<amt_border_l>0.0</amt_border_l>
				<amt_border_r>0.0</amt_border_r>
				<amt_border_kf>-1</amt_border_kf>
			</item>
			<item>
				<tx>13.407301</tx>
				<ty>0.021696</ty>
				<tz>-0.804494</tz>
				<rx>0.000000</rx>
				<ry>-0.000000</ry>
				<rz>-0.009761</rz>
				<state>1</state>
				<occlusion>-1</occlusion>
				<occlusion_kf>-1</occlusion_kf>
				<truncation>-1</truncation>
				<amt_occlusion>0.0</amt_occlusion>
				<amt_occlusion_kf>-1</amt_occlusion_kf>
				<amt_border_l>0.0</amt_border_l>
				<amt_border_r>0.0</amt_border_r>
				<amt_border_kf>-1</amt_border_kf>
			</item>
			<item>
				<tx>13.046707</tx>
				<ty>-0.005851</ty>
				<tz>-0.800087</tz>
				<rx>0.000000</rx>
				<ry>-0.000000</ry>
				<rz>-0.010742</rz>
				<state>1</state>
				<occlusion>-1</occlusion>
				<occlusion_kf>-1</occlusion_kf>
				<truncation>-1</truncation>
				<amt_occlusion>0.0</amt_occlusion>
				<amt_occlusion_kf>-1</amt_occlusion_kf>
				<amt_border_l>0.0</amt_border_l>
				<amt_border_r>0.0</amt_border_r>
				<amt_border_kf>-1</amt_border_kf>
			</item>
			<item>
				<tx>14.257985</tx>
				<ty>-0.005940</ty>
				<tz>-0.826110</tz>
				<rx>0.000000</rx>
				<ry>-0.000000</ry>
				<rz>0.000588</rz>
				<state>1</state>
				<occlusion>-1</occlusion>
				<occlusion_kf>-1</occlusion_kf>
				<truncation>-1</truncation>
				<amt_occlusion>0.0</amt_occlusion>
				<amt_occlusion_kf>-1</amt_occlusion_kf>
				<amt_border_l>0.0</amt_border_l>
				<amt_border_r>0.0</amt_border_r>
				<amt_border_kf>-1</amt_border_kf>
			</item>
			<item>
				<tx>14.422405</tx>
				<ty>-0.022970</ty>
				<tz>-0.834944</tz>
				<rx>0.000000</rx>
				<ry>-0.000000</ry>
				<rz>-0.006451</rz>
				<state>1</state>
				<occlusion>-1</occlusion>
				<occlusion_kf>-1</occlusion_kf>
				<truncation>-1</truncation>
				<amt_occlusion>0.0</amt_occlusion>
				<amt_occlusion_kf>-1</amt_occlusion_kf>
				<amt_border_l>0.0</amt_border_l>
				<amt_border_r>0.0</amt_border_r>
				<amt_border_kf>-1</amt_border_kf>
			</item>
		</poses>
		<finished>1</finished>
	</item>
</tracklets>
</boost_serialization> 
